.gitignore
CHANGES.txt
LICENSE.txt
README.rst
setup.cfg
setup.py
tox.ini
docs/.gitignore
docs/Makefile
docs/conf.py
docs/index.rst
pyramid_keystone/__init__.py
pyramid_keystone/authentication.py
pyramid_keystone/keystone.py
pyramid_keystone/settings.py
pyramid_keystone/tests.py
pyramid_keystone.egg-info/PKG-INFO
pyramid_keystone.egg-info/SOURCES.txt
pyramid_keystone.egg-info/dependency_links.txt
pyramid_keystone.egg-info/not-zip-safe
pyramid_keystone.egg-info/requires.txt
pyramid_keystone.egg-info/top_level.txt