Metadata-Version: 1.1
Name: pyramid-keystone
Version: 0.0.1.dev0
Summary: OpenStack keystone bindings for Pyramid
Home-page: https://github.com/bertjwregeer/pyramid_keystone
Author: Bert JW Regeer
Author-email: bertjw@regeer.org
License: MIT
Keywords: web wsgi pyramid keystone
Platform: UNKNOWN
Classifier: Development Status :: 1 - Planning
Classifier: Intended Audience :: Developers
Classifier: Programming Language :: Python
Classifier: Programming Language :: Python :: 3.4
Classifier: Framework :: Pyramid
Classifier: License :: OSI Approved :: MIT License
